helloworld.py
helloworld_pucsp-0.0.1.dist-info/LICENSE.txt
helloworld_pucsp-0.0.1.dist-info/METADATA
helloworld_pucsp-0.0.1.dist-info/WHEEL
helloworld_pucsp-0.0.1.dist-info/top_level.txt
helloworld_pucsp-0.0.1.dist-info/RECORD
