Metadata-Version: 2.1
Name: helloworld-pucsp
Version: 0.0.1
Summary: Say hello
Home-page: https://github.com/j3ffsilva/helloworld_pucsp
Author: Jefferson O. Silva
Author-email: silvajo@pucsp.br
License: UNKNOWN
Platform: UNKNOWN
Classifier: Programming Language :: Python :: 3
Classifier: Programming Language :: Python :: 3.6
Classifier: Programming Language :: Python :: 3.7
Classifier: License :: OSI Approved :: GNU General Public License v2 or later (GPLv2+)
Classifier: Operating System :: OS Independent
License-File: LICENSE.txt
Provides-Extra: dev
Requires-Dist: pytest (>=3.7) ; extra == 'dev'
